setup.py
insight360mlapi/__init__.py
insight360mlapi/building_energy_api.py
insight360mlapi/model_config.py
insight360mlapi/predict_gbXML.py
insight360mlapi.egg-info/PKG-INFO
insight360mlapi.egg-info/SOURCES.txt
insight360mlapi.egg-info/dependency_links.txt
insight360mlapi.egg-info/not-zip-safe
insight360mlapi.egg-info/requires.txt
insight360mlapi.egg-info/top_level.txt